checklist/__init__.py
checklist/checklist.py
checklist/reset_user_settings.py
checklist/update_preserve_user_settings.py
checklist/user_settings/__init__.py
checklist/user_settings/known_locations.pkl
checklist/user_settings/ndict.pkl
checklist/user_settings/objectives.pkl
oucass_checklist-0.3.0.dist-info/LICENSE
oucass_checklist-0.3.0.dist-info/MANIFEST.in
oucass_checklist-0.3.0.dist-info/METADATA
oucass_checklist-0.3.0.dist-info/WHEEL
oucass_checklist-0.3.0.dist-info/entry_points.txt
oucass_checklist-0.3.0.dist-info/top_level.txt
oucass_checklist-0.3.0.dist-info/RECORD
