Metadata-Version: 2.1
Name: oucass-checklist
Version: 0.3.0
Summary: Program to manage safety checks and create metadata files compatible with oucass-profiles in the field
Home-page: https://github.com/oucass/Checklist
Author: Jessica Blunt, Brian Greene
Author-email: cass@ou.edu
License: UNKNOWN
Platform: UNKNOWN
Classifier: Programming Language :: Python :: 3
Classifier: License :: OSI Approved :: GNU General Public License v3 (GPLv3)
Classifier: Operating System :: OS Independent
Requires-Python: >=3.7
Requires-Dist: click
